tensorflow_graphics/__init__.py
tensorflow_graphics/version.py
tensorflow_graphics/geometry/__init__.py
tensorflow_graphics/geometry/convolution/__init__.py
tensorflow_graphics/geometry/convolution/graph_convolution.py
tensorflow_graphics/geometry/convolution/graph_pooling.py
tensorflow_graphics/geometry/convolution/utils.py
tensorflow_graphics/geometry/convolution/tests/__init__.py
tensorflow_graphics/geometry/convolution/tests/graph_convolution_test.py
tensorflow_graphics/geometry/convolution/tests/graph_pooling_test.py
tensorflow_graphics/geometry/convolution/tests/utils_test.py
tensorflow_graphics/geometry/deformation_energy/__init__.py
tensorflow_graphics/geometry/deformation_energy/as_conformal_as_possible.py
tensorflow_graphics/geometry/deformation_energy/tests/__init__.py
tensorflow_graphics/geometry/deformation_energy/tests/as_conformal_as_possible_test.py
tensorflow_graphics/geometry/representation/__init__.py
tensorflow_graphics/geometry/representation/grid.py
tensorflow_graphics/geometry/representation/point.py
tensorflow_graphics/geometry/representation/ray.py
tensorflow_graphics/geometry/representation/triangle.py
tensorflow_graphics/geometry/representation/mesh/__init__.py
tensorflow_graphics/geometry/representation/mesh/normals.py
tensorflow_graphics/geometry/representation/mesh/utils.py
tensorflow_graphics/geometry/representation/mesh/tests/__init__.py
tensorflow_graphics/geometry/representation/mesh/tests/normals_test.py
tensorflow_graphics/geometry/representation/mesh/tests/utils_test.py
tensorflow_graphics/geometry/representation/tests/__init__.py
tensorflow_graphics/geometry/representation/tests/grid_test.py
tensorflow_graphics/geometry/representation/tests/point_test.py
tensorflow_graphics/geometry/representation/tests/ray_test.py
tensorflow_graphics/geometry/representation/tests/triangle_test.py
tensorflow_graphics/geometry/transformation/__init__.py
tensorflow_graphics/geometry/transformation/axis_angle.py
tensorflow_graphics_gpu-1.0.0.dist-info/LICENSE
tensorflow_graphics_gpu-1.0.0.dist-info/METADATA
tensorflow_graphics_gpu-1.0.0.dist-info/WHEEL
tensorflow_graphics_gpu-1.0.0.dist-info/top_level.txt
tensorflow_graphics_gpu-1.0.0.dist-info/RECORD
